<?xml version="1.0" encoding="UTF-8" standalone="yes"?>
<w:styles xmlns:r="http://schemas.openxmlformats.org/officeDocument/2006/relationships"
xmlns:w="http://schemas.openxmlformats.org/wordprocessingml/2006/main">
  <w:docDefaults>
    <w:rPrDefault>
      <w:rPr>
        <w:rFonts w:asciiTheme="minorHAnsi" w:eastAsiaTheme="minorEastAsia" w:hAnsiTheme="minorHAnsi" w:cstheme="minorBidi"/>
        <w:sz w:val="22"/>
        <w:szCs w:val="22"/>
        <w:lang w:val="en-US" w:eastAsia="en-US" w:bidi="ar-SA"/>
      </w:rPr>
    </w:rPrDefault>
    <w:pPrDefault>
      <w:pPr>
        <w:spacing w:after="200" w:line="276" w:lineRule="auto"/>
      </w:pPr>
    </w:pPrDefault>
  </w:docDefaults>
  <w:latentStyles w:defLockedState="0" w:defUIPriority="99" w:defSemiHidden="1"
 w:defUnhideWhenUsed="1" w:defQFormat="0" w:count="267">
    <w:lsdException w:name="Normal" w:semiHidden="0" w:uiPriority="0" w:unhideWhenUsed="0" w:qFormat="1"/>
    <w:lsdException w:name="heading 1" w:semiHidden="0" w:uiPriority="9" w:unhideWhenUsed="0" w:qFormat="1"/>
    <w:lsdException w:name="Title" w:semiHidden="0" w:uiPriority="10" w:unhideWhenUsed="0" w:qFormat="1"/>
    <w:lsdException w:name="Default Paragraph Font" w:uiPriority="1"/>
    <w:lsdException w:name="Subtitle" w:semiHidden="0" w:uiPriority="11" w:unhideWhenUsed="0" w:qFormat="1"/>
    <w:lsdException w:name="Strong" w:semiHidden="0" w:uiPriority="22" w:unhideWhenUsed="0" w:qFormat="1"/>
    <w:lsdException w:name="Table Grid" w:semiHidden="0" w:uiPriority="59" w:unhideWhenUsed="0"/>
    <w:lsdException w:name="Light List Accent 2" w:semiHidden="0" w:uiPriority="61" w:unhideWhenUsed="0"/>
  </w:latentStyles>
  <w:style w:type="paragraph" w:default="1" w:styleId="Normal">
    <w:name w:val="Normal"/>
    <w:qFormat/>
  </w:style>
  <w:style w:type="character" w:default="1" w:styleId="DefaultParagraphFont">
    <w:name w:val="Default Paragraph Font"/>
    <w:uiPriority w:val="1"/>
    <w:semiHidden/>
    <w:unhideWhenUsed/>
  </w:style>
  <w:style w:type="table" w:default="1" w:styleId="TableNormal">
    <w:name w:val="Normal Table"/>
    <w:uiPriority w:val="99"/>
    <w:semiHidden/>
    <w:unhideWhenUsed/>
    <w:qFormat/>
    <w:tblPr>
      <w:tblInd w:w="0" w:type="dxa"/>
      <w:tblCellMar>
        <w:top w:w="0" w:type="dxa"/>
        <w:left w:w="108" w:type="dxa"/>
        <w:bottom w:w="0" w:type="dxa"/>
        <w:right w:w="108" w:type="dxa"/>
      </w:tblCellMar>
    </w:tblPr>
  </w:style>
  <w:style w:type="table" w:styleId="LightList-Accent2">
    <w:name w:val="Light List Accent 2"/>
    <w:basedOn w:val="TableNormal"/>
    <w:uiPriority w:val="61"/>
    <w:rsid w:val="00693473"/>
    <w:pPr>
      <w:spacing w:after="0" w:line="240" w:lineRule="auto"/>
    </w:pPr>
    <w:tblPr>
      <w:tblStyleRowBandSize w:val="1"/>
      <w:tblStyleColBandSize w:val="1"/>
      <w:tblInd w:w="0" w:type="dxa"/>
      <w:tblBorders>
        <w:top w:val="single" w:sz="8" w:space="0" w:color="C0504D" w:themeColor="accent2"/>
        <w:left w:val="single" w:sz="8" w:space="0" w:color="C0504D" w:themeColor="accent2"/>
        <w:bottom w:val="single" w:sz="8" w:space="0" w:color="C0504D" w:themeColor="accent2"/>
        <w:right w:val="single" w:sz="8" w:space="0" w:color="C0504D" w:themeColor="accent2"/>
      </w:tblBorders>
      <w:tblCellMar>
        <w:top w:w="0" w:type="dxa"/>
        <w:left w:w="108" w:type="dxa"/>
        <w:bottom w:w="0" w:type="dxa"/>
        <w:right w:w="108" w:type="dxa"/>
      </w:tblCellMar>
    </w:tblPr>
    <w:tblStylePr w:type="firstRow">
      <w:pPr>
        <w:spacing w:before="0" w:after="0" w:line="240" w:lineRule="auto"/>
      </w:pPr>
      <w:rPr>
        <w:b/>
        <w:bCs/>
        <w:color w:val="FFFFFF" w:themeColor="background1"/>
      </w:rPr>
      <w:tblPr/>
      <w:tcPr>
        <w:shd w:val="clear" w:color="auto" w:fill="C0504D" w:themeFill="accent2"/>
      </w:tcPr>
    </w:tblStylePr>
    <w:tblStylePr w:type="lastRow">
      <w:pPr>
        <w:spacing w:before="0" w:after="0" w:line="240" w:lineRule="auto"/>
      </w:pPr>
      <w:rPr>
        <w:b/>
        <w:bCs/>
      </w:rPr>
      <w:tblPr/>
      <w:tcPr>
        <w:tcBorders>
          <w:top w:val="double" w:sz="6" w:space="0" w:color="C0504D" w:themeColor="accent2"/>
          <w:left w:val="single" w:sz="8" w:space="0" w:color="C0504D" w:themeColor="accent2"/>
          <w:bottom w:val="single" w:sz="8" w:space="0" w:color="C0504D" w:themeColor="accent2"/>
          <w:right w:val="single" w:sz="8" w:space="0" w:color="C0504D" w:themeColor="accent2"/>
        </w:tcBorders>
      </w:tcPr>
    </w:tblStylePr>
    <w:tblStylePr w:type="firstCol">
      <w:rPr>
        <w:b/>
        <w:bCs/>
      </w:rPr>
    </w:tblStylePr>
    <w:tblStylePr w:type="lastCol">
      <w:rPr>
        <w:b/>
        <w:bCs/>
      </w:rPr>
    </w:tblStylePr>
    <w:tblStylePr w:type="band1Vert">
      <w:tblPr/>
      <w:tcPr>
        <w:tcBorders>
          <w:top w:val="single" w:sz="8" w:space="0" w:color="C0504D" w:themeColor="accent2"/>
          <w:left w:val="single" w:sz="8" w:space="0" w:color="C0504D" w:themeColor="accent2"/>
          <w:bottom w:val="single" w:sz="8" w:space="0" w:color="C0504D" w:themeColor="accent2"/>
          <w:right w:val="single" w:sz="8" w:space="0" w:color="C0504D" w:themeColor="accent2"/>
        </w:tcBorders>
      </w:tcPr>
    </w:tblStylePr>
    <w:tblStylePr w:type="band1Horz">
      <w:tblPr/>
      <w:tcPr>
        <w:tcBorders>
          <w:top w:val="single" w:sz="8" w:space="0" w:color="C0504D" w:themeColor="accent2"/>
          <w:left w:val="single" w:sz="8" w:space="0" w:color="C0504D" w:themeColor="accent2"/>
          <w:bottom w:val="single" w:sz="8" w:space="0" w:color="C0504D" w:themeColor="accent2"/>
          <w:right w:val="single" w:sz="8" w:space="0" w:color="C0504D" w:themeColor="accent2"/>
        </w:tcBorders>
      </w:tcPr>
    </w:tblStylePr>
  </w:style>
</w:styles>
